{
  "id": "0d2055c1dbe43a48e65b93ad814ef4a1",
  "title": "School of Architecture and Planning recognizes faculty with academic promotions in 2025",
  "description": "The faculty members’ work comprises multifaceted research and scholarship across a wide range of disciplines.",
  "link": "https://news.mit.edu/2025/school-architecture-planning-recognizes-faculty-academic-promotions-0722",
  "pubDate": "Tue, 22 Jul 2025 10:00:00 -0400",
  "source": "MIT News - AI",
  "category": "techno-skeptic",
  "credibility": 0.9,
  "classified": true,
  "fetchedDate": "2025-07-23T20:01:52.323Z",
  "expiresDate": "2025-07-24T20:01:52.323Z",
  "classification": {
    "category": "techno-optimist",
    "confidence": 0,
    "provider": "fallback"
  },
  "classifiedDate": "2025-07-23T20:02:52.985Z"
}