{
  "id": "c30c336de205bcf4a8775f6be0b9dbba",
  "title": "AGI is not a milestone",
  "description": "There is no capability threshold that will lead to sudden impacts",
  "link": "https://www.aisnakeoil.com/p/agi-is-not-a-milestone",
  "pubDate": "Thu, 01 May 2025 11:47:59 GMT",
  "source": "AI Snake Oil",
  "category": "techno-skeptic",
  "credibility": 0.85,
  "classified": true,
  "fetchedDate": "2025-07-12T05:49:34.484Z",
  "expiresDate": "2025-07-13T05:49:34.484Z",
  "classification": {
    "category": "techno-optimist",
    "confidence": 0,
    "provider": "fallback"
  },
  "classifiedDate": "2025-07-12T08:02:40.402Z"
}